qbstyles/__init__.py
qbstyles/mpl_style.py
qbstyles/styles/qb-common.mplstyle
qbstyles/styles/qb-dark.mplstyle
qbstyles/styles/qb-light.mplstyle
qbstyles-0.1.4.dist-info/LICENSE
qbstyles-0.1.4.dist-info/METADATA
qbstyles-0.1.4.dist-info/WHEEL
qbstyles-0.1.4.dist-info/top_level.txt
qbstyles-0.1.4.dist-info/RECORD
