Metadata-Version: 2.1
Name: qbstyles
Version: 0.1.4
Summary: QB styles for common plotting libraries
Home-page: https://github.com/quantumblacklabs/qbstyles
Author: QuantumBlack Labs
Author-email: opensource@quantumblack.com
License: Apache 2.0
Platform: UNKNOWN
Classifier: Programming Language :: Python :: 3
Classifier: License :: OSI Approved :: Apache Software License
Classifier: Operating System :: OS Independent
Requires-Python: >=3.5
Requires-Dist: matplotlib (<4.0,>=3.0.3)
